num2rus/__init__.py
num2rus/converter.py
num2rus/main.py
num2rus/tests.py
num2rus-0.1.0.dist-info/LICENSE
num2rus-0.1.0.dist-info/METADATA
num2rus-0.1.0.dist-info/WHEEL
num2rus-0.1.0.dist-info/top_level.txt
num2rus-0.1.0.dist-info/RECORD
