Metadata-Version: 2.1
Name: num2rus
Version: 0.1.0
Summary: A small package to convert float numbers to russian string
Home-page: https://github.com/terean-dspd/numbers-2-rus
Author: DennisKot
Author-email: DennisKot@google.com
Classifier: Programming Language :: Python :: 3
Classifier: License :: OSI Approved :: MIT License
Classifier: Operating System :: OS Independent
Requires-Python: >=3.6
License-File: LICENSE
